{
    "scooters": [
      {
        "name": "~Honda Metro Scooter",
        "photo": "hondascooter350225.png",
        "events": [
          "Reservation: Half Day (3 hrs): $20",
          "Reservation: Full Day: $30",
          "Walk-In: Half Day (3 hrs): $25",
          "Walk-In: Full Day: $35"
        ]
      },
      {
        "name": "~Honda Dio Scooter",
        "photo": "hondadio350225.png",
        "events": [
          "Reservation: Half Day (3 hrs): $30",
          "Reservation: Full Day: $40",
          "Walk-In: Half Day (3 hrs): $35",
          "Walk-In: Full Day: $45"
        ]
      },
      {
        "name": "~Honda PCX150 Scooter",
        "photo": "hondapcx350225.png",
        "events": [
          "Reservation: Half Day (3 hrs): $40",
          "Reservation: Full Day: $50",
          "Walk-In: Half Day (3 hrs): $45",
          "Walk-In: Full Day: $55"
        ]
      },
      {
        "name": "Honda Pioneer ATV",
        "photo": "hondapioneer350225.png",
        "events": [
         "Reservation: Half Day (3 hrs): $50",
          "Reservation: Full Day: $70",
          "Walk-In: Half Day (3 hrs): $60",
          "Walk-In: Full Day: $80"
        ]
      },
      {
        "name": "Jeep Wrangler - 4 door with a/c",
        "photo": "jeepwrangler350225.png",
        "events": [
          "Reservation: Half Day (3 hrs): $70",
          "Reservation: Full Day: $100",
          "Walk-In: Half Day (3 hrs): $85",
          "Walk-In: Full Day: $125"
        ]
      },
      {
        "name": "Jeep Wrangler - 2 door",
        "photo": "jeepwrangler2dr350225.png",
        "events": [
          "Reservation: Half Day (3 hrs): $60",
          "Reservation: Full Day: $85",
          "Walk-In: Half Day (3 hrs): $70",
          "Walk-In: Full Day: $90"
        ]
      }
    ]
  }